libsql_experimental-0.0.54.dist-info/METADATA
libsql_experimental-0.0.54.dist-info/WHEEL
libsql_experimental-0.0.54.dist-info/licenses/LICENSE.md
libsql_experimental/__init__.py
libsql_experimental/libsql_experimental.cpython-311-darwin.so
libsql_experimental-0.0.54.dist-info/RECORD
