Metadata-Version: 2.4
Name: libsql-experimental
Version: 0.0.54
Classifier: Programming Language :: Rust
Classifier: Programming Language :: Python :: Implementation :: CPython
Classifier: Programming Language :: Python :: Implementation :: PyPy
License-File: LICENSE.md
Requires-Python: >=3.7
